{"Home":["SugarCane","SugarCane","SugarCane","SugarCane","Пилон(Ошибка)","SugarCane","Пилон(Ошибка)","SugarCane","TitanGlassRoom","SugarCane","SugarCane","SugarCane","SugarCane","SugarCane","SugarCane","SugarCane","TitanGlassRoom","TankovayaPushkaStrelaushzayaTankamikotorieStrelyayootTankami","SugarCane","Пилон(Ошибка)","SugarCane","SugarCane","SugarCane","SugarCane","SugarCane","SugarCane","SugarCane","SugarCane","SugarCane","SugarCane","Автомат_С_Газировкой","Пилон(Ошибка)","SugarCane","TitanGlassRoom","SugarCane","SugarCane","SugarCane","Автомат_С_Газировкой","SugarCane","Автомат_С_Газировкой","SugarCane","TitanGlassRoom","Автомат_С_Газировкой","Автомат_С_Газировкой","TankovayaPushkaStrelaushzayaTankamikotorieStrelyayootTankami","SugarCane","SugarCane","SugarCane","SugarCane","SugarCane","Автомат_С_Газировкой","SugarCane","SugarCane","SugarCane","SugarCane","SugarCane","Пилон(Ошибка)","Автомат_С_Газировкой","SugarCane","Автомат_С_Газировкой","SugarCane","Автомат_С_Газировкой","SugarCane","Пилон(Ошибка)","SugarCane","SugarCane","SugarCane","Автомат_С_Газировкой","yuminike","Дошик","Sugar","Sugar","Дошик","yuminike","yuminike","Sugar","SugarCane","Пилон(Ошибка)","Автомат_С_Газировкой","Дошик","Sugar","yuminike","Sugar","Пилон(Ошибка)","TreeCrasher","Sugar","yuminike","Бидон_С_CUM","Бидон_С_CUM","Бидон_С_CUM","Деньги","Sugar","Пилон(Ошибка)","Sugar","Пилон(Ошибка)","Sugar","yuminike","Sugar","Sugar","Бидон_С_CUM","Sugar","Бидон_С_CUM","SugarCane","TitanGlassRoom","SugarCane","Sugar","Sugar","Деньги","Sugar","SugarCane","Пилон(Ошибка)","SugarCane","Автомат_С_Газировкой","SugarCane","Sugar","yuminike","Sugar","Автомат_С_Газировкой","Дошик","Sugar","Деньги","Sugar","Sugar","Бидон_С_CUM","Бидон_С_CUM","Катапульта","Sugar","Sugar","Sugar","yuminike","yuminike","Sugar","Бидон_С_CUM","TreeCrasher","yuminike","Sugar","Sugar","SugarCane","Sugar","Дошик","Sugar","Sugar","Деньги","Sugar","Пилон(Ошибка)","Sugar","Sugar","Бидон_С_CUM","TitanGlassRoom","Пилон(Ошибка)","Пилон(Ошибка)","GMCS","Sugar","Бидон_С_CUM","Автомат_С_Газировкой","Автомат_С_Газировкой","Sugar","TankovayaPushkaStrelaushzayaTankamikotorieStrelyayootTankami","АлтарьАртифакт","Sugar","Sugar","Бидон_С_CUM","SugarCane","Бидон_С_CUM","Sugar","SugarCane","Sugar","Sugar","SugarCane","Бидон_С_CUM","Бидон_С_CUM","Sugar","Пилон(Ошибка)","Бидон_С_CUM","Sugar","Sugar","Деньги","SugarCane","Sugar","Sugar","Sugar","yuminike","Sugar","SugarCane","Бидон_С_CUM","Sugar","Автомат_С_Газировкой","Sugar","Sugar","Деньги","Камод","SugarCane","Дошик","SugarCane","SugarCane","Sugar","SugarCane","yuminike","Sugar","Дошик","Дошик","Дошик","Бидон_С_CUM","Пилон(Ошибка)","Sugar","Бидон_С_CUM","Sugar","Sugar","Пилон(Ошибка)","Sugar","Sugar","Деньги","SugarCane","Пилон(Ошибка)","Бидон_С_CUM","Пилон(Ошибка)","Бидон_С_CUM","yuminike","Деньги","Sugar","Пилон(Ошибка)","Дошик","Sugar","yuminike","Sugar","Sugar","Автомат_С_Газировкой","Sugar","SugarCane","Sugar","Sugar","Sugar","TreeCrasher","Пилон(Ошибка)","Sugar","Бидон_С_CUM","Sugar","Деньги","Автомат_С_Газировкой","Sugar","SugarCane","Автомат_С_Газировкой","Sugar","Sugar","Sugar","yuminike","Бидон_С_CUM","yuminike","SugarCane","Деньги","Sugar","Бидон_С_CUM","Пилон(Ошибка)","Sugar","Бидон_С_CUM","Бидон_С_CUM","SugarCane","Sugar","Sugar","Sugar","Sugar","Sugar","Какос","SugarCane","yuminike","Sugar","Sugar","Sugar","Sugar","yuminike","yuminike","Sugar","Катапульта","Бидон_С_CUM","Sugar","Sugar","Sugar","Sugar","Sugar","Бидон_С_CUM","yuminike","yuminike","Sugar","SugarCane","Sugar","Sugar","Бидон_С_CUM","Sugar","Sugar","Пилон(Ошибка)","Автомат_С_Газировкой"],"Pos":[{"x":-0.39106833934783938,"y":0.030000686645507814,"z":-34.58846664428711},{"x":-10.754706382751465,"y":0.030000686645507814,"z":-44.99432373046875},{"x":-22.542314529418947,"y":0.030000686645507814,"z":-22.61521339416504},{"x":-17.99127769470215,"y":0.030000686645507814,"z":-34.58846664428711},{"x":-22.789148330688478,"y":0.030000686645507814,"z":-2.5288689136505129},{"x":3.8433687686920168,"y":0.030000686645507814,"z":-22.61521339416504},{"x":-13.023807525634766,"y":0.030000686645507814,"z":-8.600126266479493},{"x":-22.019729614257814,"y":0.030000686645507814,"z":5.2596635818481449},{"x":-3.405184507369995,"y":0.030000686645507814,"z":-35.48557662963867},{"x":-31.167259216308595,"y":0.030000686645507814,"z":5.2596635818481449},{"x":-27.046600341796876,"y":0.030000686645507814,"z":-44.99432373046875},{"x":-3.4398462772369386,"y":0.030000686645507814,"z":0.605513334274292},{"x":-10.239986419677735,"y":0.030000686645507814,"z":5.2596635818481449},{"x":-35.19119644165039,"y":0.030000686645507814,"z":-2.6680896282196047},{"x":-13.76966381072998,"y":0.030000686645507814,"z":-22.61521339416504},{"x":-35.19119644165039,"y":0.030000686645507814,"z":-12.405362129211426},{"x":22.79588508605957,"y":0.030000686645507814,"z":-35.48557662963867},{"x":14.705540657043457,"y":0.030000686645507814,"z":-44.99432373046875},{"x":-35.19119644165039,"y":0.030000686645507814,"z":-21.12586784362793},{"x":-13.023807525634766,"y":0.030000686645507814,"z":-2.6155943870544435},{"x":-20.890995025634767,"y":0.030000686645507814,"z":-9.79147720336914},{"x":-3.4398462772369386,"y":0.030000686645507814,"z":-7.321683406829834},{"x":-28.24742317199707,"y":0.030000686645507814,"z":-34.58846664428711},{"x":-17.957984924316408,"y":0.030000686645507814,"z":-44.99432373046875},{"x":-37.00784683227539,"y":0.030000686645507814,"z":-44.99432373046875},{"x":-10.906761169433594,"y":0.030000686645507814,"z":-34.58846664428711},{"x":-5.145684242248535,"y":0.030000686645507814,"z":-22.61521339416504},{"x":-35.19119644165039,"y":0.030000686645507814,"z":-30.405189514160158},{"x":-0.3325676918029785,"y":0.030000686645507814,"z":-44.99432373046875},{"x":-17.99127769470215,"y":0.030000686645507814,"z":-34.58846664428711},{"x":36.96030044555664,"y":0.030000686645507814,"z":-47.36283493041992},{"x":-22.789148330688478,"y":0.030000686645507814,"z":-2.5288689136505129},{"x":-22.019729614257814,"y":0.030000686645507814,"z":5.2596635818481449},{"x":-3.405184507369995,"y":0.030000686645507814,"z":-35.48557662963867},{"x":-31.167259216308595,"y":0.030000686645507814,"z":5.2596635818481449},{"x":-27.046600341796876,"y":0.030000686645507814,"z":-44.99432373046875},{"x":-3.4398462772369386,"y":0.030000686645507814,"z":0.605513334274292},{"x":26.165082931518556,"y":0.030000686645507814,"z":-29.566837310791017},{"x":-10.239986419677735,"y":0.030000686645507814,"z":5.2596635818481449},{"x":26.165082931518556,"y":0.030000686645507814,"z":-37.97858810424805},{"x":-13.76966381072998,"y":0.030000686645507814,"z":-22.61521339416504},{"x":22.79588508605957,"y":0.030000686645507814,"z":-35.48557662963867},{"x":16.57554054260254,"y":0.030000686645507814,"z":-9.832772254943848},{"x":26.165082931518556,"y":0.030000686645507814,"z":-20.75141716003418},{"x":14.705540657043457,"y":0.030000686645507814,"z":-44.99432373046875},{"x":-20.890995025634767,"y":0.030000686645507814,"z":-9.79147720336914},{"x":-3.4398462772369386,"y":0.030000686645507814,"z":-7.321683406829834},{"x":-28.24742317199707,"y":0.030000686645507814,"z":-34.58846664428711},{"x":-37.00784683227539,"y":0.030000686645507814,"z":-44.99432373046875},{"x":-5.145684242248535,"y":0.030000686645507814,"z":-22.61521339416504},{"x":36.96030044555664,"y":0.030000686645507814,"z":-38.17258834838867},{"x":-0.3325676918029785,"y":0.030000686645507814,"z":-44.99432373046875},{"x":-0.39106833934783938,"y":0.030000686645507814,"z":-34.58846664428711},{"x":-10.754706382751465,"y":0.030000686645507814,"z":-44.99432373046875},{"x":-22.542314529418947,"y":0.030000686645507814,"z":-22.61521339416504},{"x":3.8433687686920168,"y":0.030000686645507814,"z":-22.61521339416504},{"x":-13.023807525634766,"y":0.030000686645507814,"z":-8.600126266479493},{"x":26.165082931518556,"y":0.030000686645507814,"z":-9.832772254943848},{"x":-35.19119644165039,"y":0.030000686645507814,"z":-2.6680896282196047},{"x":16.57554054260254,"y":0.030000686645507814,"z":-19.469099044799806},{"x":-35.19119644165039,"y":0.030000686645507814,"z":-12.405362129211426},{"x":26.165082931518556,"y":0.030000686645507814,"z":-47.36283493041992},{"x":-35.19119644165039,"y":0.030000686645507814,"z":-21.12586784362793},{"x":-13.023807525634766,"y":0.030000686645507814,"z":-2.6155943870544435},{"x":-17.957984924316408,"y":0.030000686645507814,"z":-44.99432373046875},{"x":-10.906761169433594,"y":0.030000686645507814,"z":-34.58846664428711},{"x":-35.19119644165039,"y":0.030000686645507814,"z":-30.405189514160158},{"x":16.57554054260254,"y":0.030000686645507814,"z":-27.91436195373535},{"x":-32.83240509033203,"y":0.030000686645507814,"z":-10.510164260864258},{"x":44.211246490478519,"y":0.030000686645507814,"z":-3.8327150344848635},{"x":-28.24742317199707,"y":6.030000686645508,"z":-33.58846664428711},{"x":-35.19119644165039,"y":6.030000686645508,"z":-1.6680896282196046},{"x":41.792564392089847,"y":0.030000686645507814,"z":-13.055527687072754},{"x":-20.24302864074707,"y":0.030000686645507814,"z":-25.493497848510743},{"x":-18.232398986816408,"y":0.030000686645507814,"z":-58.60468292236328},{"x":-17.957984924316408,"y":6.030000686645508,"z":-45.99432373046875},{"x":-17.99127769470215,"y":0.030000686645507814,"z":-34.58846664428711},{"x":-18.94451904296875,"y":0.030000686645507814,"z":-18.326881408691408},{"x":36.96030044555664,"y":0.030000686645507814,"z":-47.36283493041992},{"x":44.211246490478519,"y":0.030000686645507814,"z":-21.62818145751953},{"x":-37.00784683227539,"y":6.030000686645508,"z":-45.99432373046875},{"x":-29.604421615600587,"y":0.030000686645507814,"z":-35.50947952270508},{"x":-0.39106833934783938,"y":6.030000686645508,"z":-35.58846664428711},{"x":-17.886524200439454,"y":0.030000686645507814,"z":-25.742319107055665},{"x":12.577134132385254,"y":0.030000686645507814,"z":0.4784139096736908},{"x":-13.76966381072998,"y":6.030000686645508,"z":-23.61521339416504},{"x":-8.019659042358399,"y":0.030000686645507814,"z":-19.611589431762697},{"x":56.91798782348633,"y":0.030000686645507814,"z":-9.809814453125},{"x":51.52730941772461,"y":0.030000686645507814,"z":-0.16389629244804383},{"x":56.91798782348633,"y":0.030000686645507814,"z":2.31835675239563},{"x":41.037925720214847,"y":0.030000686645507814,"z":11.229820251464844},{"x":-21.019729614257814,"y":6.030000686645508,"z":5.2596635818481449},{"x":-22.789148330688478,"y":0.030000686645507814,"z":-2.5288689136505129},{"x":-31.167259216308595,"y":6.030000686645508,"z":4.2596635818481449},{"x":-27.17951202392578,"y":0.030000686645507814,"z":-22.36934471130371},{"x":-34.19119644165039,"y":6.030000686645508,"z":-12.405362129211426},{"x":-29.604421615600587,"y":0.030000686645507814,"z":-44.86982345581055},{"x":-35.19119644165039,"y":6.030000686645508,"z":-3.6680896282196047},{"x":-14.76966381072998,"y":6.030000686645508,"z":-22.61521339416504},{"x":48.6215705871582,"y":0.030000686645507814,"z":0.1966400146484375},{"x":-21.542314529418947,"y":6.030000686645508,"z":-22.61521339416504},{"x":48.6215705871582,"y":0.030000686645507814,"z":-5.031157493591309},{"x":-22.019729614257814,"y":0.030000686645507814,"z":5.2596635818481449},{"x":-3.405184507369995,"y":0.030000686645507814,"z":-35.48557662963867},{"x":-31.167259216308595,"y":0.030000686645507814,"z":5.2596635818481449},{"x":-9.906761169433594,"y":6.030000686645508,"z":-34.58846664428711},{"x":3.8433687686920168,"y":6.030000686645508,"z":-23.61521339416504},{"x":38.01144027709961,"y":0.030000686645507814,"z":11.229820251464844},{"x":-36.19119644165039,"y":6.030000686645508,"z":-30.405189514160158},{"x":-27.046600341796876,"y":0.030000686645507814,"z":-44.99432373046875},{"x":-27.44264030456543,"y":0.030000686645507814,"z":-14.339805603027344},{"x":-3.4398462772369386,"y":0.030000686645507814,"z":0.605513334274292},{"x":26.165082931518556,"y":0.030000686645507814,"z":-29.566837310791017},{"x":-10.239986419677735,"y":0.030000686645507814,"z":5.2596635818481449},{"x":-17.957984924316408,"y":6.030000686645508,"z":-43.99432373046875},{"x":-10.549622535705567,"y":0.030000686645507814,"z":-14.36021614074707},{"x":-34.19119644165039,"y":6.030000686645508,"z":-21.12586784362793},{"x":26.165082931518556,"y":0.030000686645507814,"z":-37.97858810424805},{"x":41.792564392089847,"y":0.030000686645507814,"z":-19.060808181762697},{"x":-36.19119644165039,"y":6.030000686645508,"z":-12.405362129211426},{"x":35.787288665771487,"y":0.030000686645507814,"z":13.370232582092286},{"x":-13.76966381072998,"y":6.030000686645508,"z":-21.61521339416504},{"x":-10.754706382751465,"y":6.030000686645508,"z":-43.99432373046875},{"x":52.98578643798828,"y":0.030000686645507814,"z":-5.979158401489258},{"x":56.91798782348633,"y":0.030000686645507814,"z":-6.39328670501709},{"x":-50.639625549316409,"y":0.030000686645507814,"z":-16.260900497436525},{"x":-19.890995025634767,"y":6.030000686645508,"z":-9.79147720336914},{"x":-35.19119644165039,"y":6.030000686645508,"z":-29.405189514160158},{"x":-27.046600341796876,"y":6.030000686645508,"z":-43.99432373046875},{"x":-44.33317947387695,"y":0.030000686645507814,"z":-34.8123779296875},{"x":-44.33317947387695,"y":0.030000686645507814,"z":-24.552597045898439},{"x":-18.957984924316408,"y":6.030000686645508,"z":-44.99432373046875},{"x":55.67258071899414,"y":0.030000686645507814,"z":0.16041778028011323},{"x":13.6663818359375,"y":0.030000686645507814,"z":-54.16706848144531},{"x":-30.323976516723634,"y":0.030000686645507814,"z":-25.493497848510743},{"x":-11.239986419677735,"y":6.030000686645508,"z":5.2596635818481449},{"x":-16.99127769470215,"y":6.030000686645508,"z":-34.58846664428711},{"x":-13.76966381072998,"y":0.030000686645507814,"z":-22.61521339416504},{"x":-0.3325676918029785,"y":6.030000686645508,"z":-45.99432373046875},{"x":41.792564392089847,"y":0.030000686645507814,"z":-5.664143085479736},{"x":-9.239986419677735,"y":6.030000686645508,"z":5.2596635818481449},{"x":-9.754706382751465,"y":6.030000686645508,"z":-44.99432373046875},{"x":43.20237350463867,"y":0.030000686645507814,"z":9.291171073913575},{"x":-36.00784683227539,"y":6.030000686645508,"z":-44.99432373046875},{"x":-28.433828353881837,"y":0.030000686645507814,"z":-33.88434982299805},{"x":-32.167259216308597,"y":6.030000686645508,"z":5.2596635818481449},{"x":-3.4398462772369386,"y":6.030000686645508,"z":-6.321683406829834},{"x":51.52730941772461,"y":0.030000686645507814,"z":-3.6473731994628908},{"x":22.79588508605957,"y":0.030000686645507814,"z":-35.48557662963867},{"x":-15.004979133605957,"y":0.030000686645507814,"z":-33.88434982299805},{"x":-20.476734161376954,"y":0.030000686645507814,"z":-14.339805603027344},{"x":-60.311241149902347,"y":0.030000686645507814,"z":-50.31909942626953},{"x":-22.542314529418947,"y":6.030000686645508,"z":-21.61521339416504},{"x":51.52730941772461,"y":0.030000686645507814,"z":-8.453667640686036},{"x":16.57554054260254,"y":0.030000686645507814,"z":-9.832772254943848},{"x":26.165082931518556,"y":0.030000686645507814,"z":-20.75141716003418},{"x":-12.76966381072998,"y":6.030000686645508,"z":-22.61521339416504},{"x":14.705540657043457,"y":0.030000686645507814,"z":-44.99432373046875},{"x":48.6215705871582,"y":0.030000686645507814,"z":-15.861909866333008},{"x":4.8433685302734379,"y":6.030000686645508,"z":-22.61521339416504},{"x":-35.19119644165039,"y":6.030000686645508,"z":-22.12586784362793},{"x":53.94561004638672,"y":0.030000686645507814,"z":-3.093632698059082},{"x":-20.890995025634767,"y":0.030000686645507814,"z":-9.79147720336914},{"x":53.94561004638672,"y":0.030000686645507814,"z":4.946003437042236},{"x":0.6674323081970215,"y":6.030000686645508,"z":-44.99432373046875},{"x":-3.4398462772369386,"y":0.030000686645507814,"z":-7.321683406829834},{"x":-10.754706382751465,"y":6.030000686645508,"z":-45.99432373046875},{"x":-11.906761169433594,"y":6.030000686645508,"z":-34.58846664428711},{"x":-28.24742317199707,"y":0.030000686645507814,"z":-34.58846664428711},{"x":56.91798782348633,"y":0.030000686645507814,"z":-0.5235176086425781},{"x":52.98578643798828,"y":0.030000686645507814,"z":-8.89606761932373},{"x":-10.906761169433594,"y":6.030000686645508,"z":-33.58846664428711},{"x":-21.93156623840332,"y":0.030000686645507814,"z":-33.88434982299805},{"x":55.67258071899414,"y":0.030000686645507814,"z":-3.8612921237945558},{"x":-10.239986419677735,"y":6.030000686645508,"z":6.2596635818481449},{"x":-35.19119644165039,"y":6.030000686645508,"z":-11.405362129211426},{"x":46.092498779296878,"y":0.030000686645507814,"z":13.370232582092286},{"x":-37.00784683227539,"y":0.030000686645507814,"z":-44.99432373046875},{"x":-21.890995025634767,"y":6.030000686645508,"z":-9.79147720336914},{"x":-34.19119644165039,"y":6.030000686645508,"z":-2.6680896282196047},{"x":-3.4398462772369386,"y":6.030000686645508,"z":-0.394486665725708},{"x":-18.079029083251954,"y":0.030000686645507814,"z":-14.36021614074707},{"x":-5.145684242248535,"y":6.030000686645508,"z":-21.61521339416504},{"x":-5.145684242248535,"y":0.030000686645507814,"z":-22.61521339416504},{"x":55.650089263916019,"y":0.030000686645507814,"z":0.8769599795341492},{"x":-10.906761169433594,"y":6.030000686645508,"z":-35.58846664428711},{"x":36.96030044555664,"y":0.030000686645507814,"z":-38.17258834838867},{"x":-28.24742317199707,"y":6.030000686645508,"z":-35.58846664428711},{"x":-37.00784683227539,"y":6.030000686645508,"z":-43.99432373046875},{"x":39.0423583984375,"y":0.030000686645507814,"z":9.291171073913575},{"x":-47.59162521362305,"y":0.030000686645507814,"z":-32.194915771484378},{"x":-0.3325676918029785,"y":0.030000686645507814,"z":-44.99432373046875},{"x":41.792564392089847,"y":0.030000686645507814,"z":-22.560436248779298},{"x":-0.39106833934783938,"y":0.030000686645507814,"z":-34.58846664428711},{"x":-10.754706382751465,"y":0.030000686645507814,"z":-44.99432373046875},{"x":-3.4398462772369386,"y":6.030000686645508,"z":1.605513334274292},{"x":-22.542314529418947,"y":0.030000686645507814,"z":-22.61521339416504},{"x":-32.91417694091797,"y":0.030000686645507814,"z":-10.510164260864258},{"x":-31.167259216308595,"y":6.030000686645508,"z":6.2596635818481449},{"x":44.211246490478519,"y":0.030000686645507814,"z":-8.869433403015137},{"x":44.211246490478519,"y":0.030000686645507814,"z":-17.182140350341798},{"x":44.211246490478519,"y":0.030000686645507814,"z":-12.985506057739258},{"x":55.650089263916019,"y":0.030000686645507814,"z":-1.8995192050933838},{"x":-37.296714782714847,"y":0.030000686645507814,"z":-33.88434982299805},{"x":-3.4398462772369386,"y":6.030000686645508,"z":-8.321683883666993},{"x":53.94561004638672,"y":0.030000686645507814,"z":0.3785263001918793},{"x":-20.890995025634767,"y":6.030000686645508,"z":-10.79147720336914},{"x":-17.99127769470215,"y":6.030000686645508,"z":-33.58846664428711},{"x":-26.47801399230957,"y":0.030000686645507814,"z":-25.742319107055665},{"x":-38.00784683227539,"y":6.030000686645508,"z":-44.99432373046875},{"x":2.8433687686920168,"y":6.030000686645508,"z":-22.61521339416504},{"x":34.590782165527347,"y":0.030000686645507814,"z":9.291171073913575},{"x":3.8433687686920168,"y":0.030000686645507814,"z":-22.61521339416504},{"x":-8.755666732788086,"y":0.030000686645507814,"z":-30.046064376831056},{"x":55.67258071899414,"y":0.030000686645507814,"z":-7.184878349304199},{"x":-13.023807525634766,"y":0.030000686645507814,"z":-8.600126266479493},{"x":53.94561004638672,"y":0.030000686645507814,"z":-6.809924125671387},{"x":-30.323976516723634,"y":0.030000686645507814,"z":-16.747167587280275},{"x":39.46963119506836,"y":0.030000686645507814,"z":13.370232582092286},{"x":-27.24742317199707,"y":6.030000686645508,"z":-34.58846664428711},{"x":-22.44586944580078,"y":0.030000686645507814,"z":-25.742319107055665},{"x":41.792564392089847,"y":0.030000686645507814,"z":-9.22404670715332},{"x":-22.019729614257814,"y":6.030000686645508,"z":6.2596635818481449},{"x":-20.24302864074707,"y":0.030000686645507814,"z":-35.50947952270508},{"x":-17.99127769470215,"y":6.030000686645508,"z":-35.58846664428711},{"x":-28.046600341796876,"y":6.030000686645508,"z":-44.99432373046875},{"x":26.165082931518556,"y":0.030000686645507814,"z":-9.832772254943848},{"x":-22.019729614257814,"y":6.030000686645508,"z":4.2596635818481449},{"x":-35.19119644165039,"y":0.030000686645507814,"z":-2.6680896282196047},{"x":-20.890995025634767,"y":6.030000686645508,"z":-8.79147720336914},{"x":-2.4398462772369386,"y":6.030000686645508,"z":-7.321683406829834},{"x":-35.19119644165039,"y":6.030000686645508,"z":-31.405189514160158},{"x":30.74846649169922,"y":0.030000686645507814,"z":-28.1650447845459},{"x":-8.755666732788086,"y":0.030000686645507814,"z":-23.774383544921876},{"x":-5.145684242248535,"y":6.030000686645508,"z":-23.61521339416504},{"x":52.98578643798828,"y":0.030000686645507814,"z":1.7773686647415162},{"x":0.6089316606521606,"y":6.030000686645508,"z":-34.58846664428711},{"x":42.47349166870117,"y":0.030000686645507814,"z":13.370232582092286},{"x":16.57554054260254,"y":0.030000686645507814,"z":-19.469099044799806},{"x":-0.39106833934783938,"y":6.030000686645508,"z":-33.58846664428711},{"x":-35.19119644165039,"y":0.030000686645507814,"z":-12.405362129211426},{"x":26.165082931518556,"y":0.030000686645507814,"z":-47.36283493041992},{"x":-26.046600341796876,"y":6.030000686645508,"z":-44.99432373046875},{"x":-6.145684242248535,"y":6.030000686645508,"z":-22.61521339416504},{"x":-36.19119644165039,"y":6.030000686645508,"z":-2.6680896282196047},{"x":-8.121280670166016,"y":0.030000686645507814,"z":-10.510164260864258},{"x":52.98578643798828,"y":0.030000686645507814,"z":-2.3442232608795168},{"x":-28.771093368530275,"y":0.030000686645507814,"z":-6.183578014373779},{"x":-35.19119644165039,"y":0.030000686645507814,"z":-21.12586784362793},{"x":34.91233444213867,"y":0.030000686645507814,"z":11.229820251464844},{"x":-35.19119644165039,"y":6.030000686645508,"z":-20.12586784362793},{"x":56.91798782348633,"y":0.030000686645507814,"z":4.501318454742432},{"x":-13.023807525634766,"y":0.030000686645507814,"z":-2.6155943870544435},{"x":-34.19119644165039,"y":6.030000686645508,"z":-30.405189514160158},{"x":55.650089263916019,"y":0.030000686645507814,"z":-7.5693817138671879},{"x":51.52730941772461,"y":0.030000686645507814,"z":3.808600425720215},{"x":-17.957984924316408,"y":0.030000686645507814,"z":-44.99432373046875},{"x":-23.019729614257814,"y":6.030000686645508,"z":5.2596635818481449},{"x":-1.3910683393478394,"y":6.030000686645508,"z":-34.58846664428711},{"x":-0.3325676918029785,"y":6.030000686645508,"z":-43.99432373046875},{"x":-29.24742317199707,"y":6.030000686645508,"z":-34.58846664428711},{"x":-2.4398462772369386,"y":6.030000686645508,"z":0.605513334274292},{"x":-10.870851516723633,"y":0.030000686645507814,"z":-32.194915771484378},{"x":-10.906761169433594,"y":0.030000686645507814,"z":-34.58846664428711},{"x":-18.326568603515626,"y":0.030000686645507814,"z":-44.96172332763672},{"x":-10.239986419677735,"y":6.030000686645508,"z":4.2596635818481449},{"x":-18.99127769470215,"y":6.030000686645508,"z":-34.58846664428711},{"x":-4.439846038818359,"y":6.030000686645508,"z":0.605513334274292},{"x":-16.957984924316408,"y":6.030000686645508,"z":-44.99432373046875},{"x":-8.019659042358399,"y":0.030000686645507814,"z":-29.602750778198243},{"x":-8.019659042358399,"y":0.030000686645507814,"z":-48.30510711669922},{"x":-4.439846038818359,"y":6.030000686645508,"z":-7.321683406829834},{"x":-64.89399719238281,"y":0.030000686645507814,"z":-13.900247573852539},{"x":56.91798782348633,"y":0.030000686645507814,"z":-3.3023757934570314},{"x":-23.542314529418947,"y":6.030000686645508,"z":-22.61521339416504},{"x":-36.19119644165039,"y":6.030000686645508,"z":-21.12586784362793},{"x":-35.19119644165039,"y":6.030000686645508,"z":-13.405362129211426},{"x":-30.167259216308595,"y":6.030000686645508,"z":5.2596635818481449},{"x":-22.542314529418947,"y":6.030000686645508,"z":-23.61521339416504},{"x":55.650089263916019,"y":0.030000686645507814,"z":-5.191922187805176},{"x":-8.019659042358399,"y":0.030000686645507814,"z":-38.94984817504883},{"x":-17.904499053955079,"y":0.030000686645507814,"z":-10.510164260864258},{"x":3.8433687686920168,"y":6.030000686645508,"z":-21.61521339416504},{"x":-35.19119644165039,"y":0.030000686645507814,"z":-30.405189514160158},{"x":-4.145684242248535,"y":6.030000686645508,"z":-22.61521339416504},{"x":-11.754706382751465,"y":6.030000686645508,"z":-44.99432373046875},{"x":53.94561004638672,"y":0.030000686645507814,"z":-10.886643409729004},{"x":-27.046600341796876,"y":6.030000686645508,"z":-45.99432373046875},{"x":-1.3325676918029786,"y":6.030000686645508,"z":-44.99432373046875},{"x":-14.122124671936036,"y":0.030000686645507814,"z":-18.326881408691408},{"x":16.57554054260254,"y":0.030000686645507814,"z":-27.91436195373535}]}